{
    "took": 1,
    "timed_out": false,
    "_shards": {
        "total": 1,
        "successful": 1,
        "skipped": 0,
        "failed": 0
    },
    "hits": {
        "total": {
            "value": 4,
            "relation": "eq"
        },
        "max_score": 1.0,
        "hits": [
            {
                "_index": "carshop",
                "_type": "review",
                "_id": "2",
                "_score": 1.0,
                "_source": {
                    "title": "Хороший магазин с приятными менеджерами.",
                    "content": "<p>Хочу поблагодарить за хороших сотрудников в офисе. Сегодня покупал масляный фильтр и получил предпраздничное настроение в беседе с менеджерами и еще и скидку) Приятно! С наступающими и хороших продаж в новом году!!!)<p>",
                    "tags": [
                        "запчасти",
                        "респект"
                    ],
                    "published_at": "2021-03-14T20:44:45+00:00"
                }
            },
            {
                "_index": "carshop",
                "_type": "review",
                "_id": "1",
                "_score": 1.0,
                "_source": {
                    "title": "Отзыв на магазин запчастей",
                    "content": "<p>Обычный перекупщик . За качеством и оригинальностью запчастей не следит вообще ! Остерегайтесь покупать у них ОРИГИНАЛ из их собственного НАЛИЧИЯ .В большинстве случаев придёт \" оригинал \" родом с китайской алибабы.<p>",
                    "tags": [
                        "запчасти",
                        "мусор"
                    ],
                    "published_at": "2021-03-14T20:44:42+00:00"
                }
            },
            {
                "_index": "carshop",
                "_type": "review",
                "_id": "3",
                "_score": 1.0,
                "_source": {
                    "title": "Хороший магазин с приятными менеджерами модернизированный.",
                    "content": "<p>Хочу поблагодарить за хороших сотрудников в офисе. Сегодня покупал масляный фильтр и получил предпраздничное настроение в беседе с менеджерами и еще и скидку) Приятно! С наступающими и хороших продаж в новом году!!!)<p>",
                    "tags": [
                        "запчасти",
                        "респект"
                    ],
                    "published_at": "2021-03-14T20:44:45+00:00"
                }
            },
            {
                "_index": "carshop",
                "_type": "review",
                "_id": "4wRPO3gBPLceILoMH3PU",
                "_score": 1.0,
                "_source": {
                    "title": "Тест",
                    "content": "Новый отзыв",
                    "tags": [
                        "первый",
                        "второй"
                    ]
                }
            }
        ]
    }
}